README.md
setup.py
ast2call/__init__.py
ast2call.egg-info/PKG-INFO
ast2call.egg-info/SOURCES.txt
ast2call.egg-info/dependency_links.txt
ast2call.egg-info/entry_points.txt
ast2call.egg-info/top_level.txt