Metadata-Version: 2.1
Name: ast2call
Version: 0.1.0
Summary: Transform python source into ast module calls
Home-page: https://github.com/antonpaquin/ast2call
Author: Anton Paquin
Author-email: python@antonpaqu.in
License: UNKNOWN
Platform: UNKNOWN
